guardrails/__init__.py
guardrails/_base_client.py
guardrails/_streaming.py
guardrails/agents.py
guardrails/cli.py
guardrails/client.py
guardrails/context.py
guardrails/exceptions.py
guardrails/py.typed
guardrails/registry.py
guardrails/runtime.py
guardrails/spec.py
guardrails/types.py
guardrails/checks/__init__.py
guardrails/checks/text/__init__.py
guardrails/checks/text/competitors.py
guardrails/checks/text/hallucination_detection.py
guardrails/checks/text/jailbreak.py
guardrails/checks/text/keywords.py
guardrails/checks/text/llm_base.py
guardrails/checks/text/moderation.py
guardrails/checks/text/nsfw.py
guardrails/checks/text/off_topic_prompts.py
guardrails/checks/text/pii.py
guardrails/checks/text/prompt_injection_detection.py
guardrails/checks/text/secret_keys.py
guardrails/checks/text/urls.py
guardrails/checks/text/user_defined_llm.py
guardrails/evals/.gitignore
guardrails/evals/README.md
guardrails/evals/__init__.py
guardrails/evals/guardrail_evals.py
guardrails/evals/core/__init__.py
guardrails/evals/core/async_engine.py
guardrails/evals/core/benchmark_calculator.py
guardrails/evals/core/benchmark_reporter.py
guardrails/evals/core/calculator.py
guardrails/evals/core/json_reporter.py
guardrails/evals/core/jsonl_loader.py
guardrails/evals/core/latency_tester.py
guardrails/evals/core/types.py
guardrails/evals/core/validate_dataset.py
guardrails/evals/core/visualizer.py
guardrails/evals/eval_demo/demo_config.json
guardrails/evals/eval_demo/demo_data.jsonl
guardrails/resources/chat/__init__.py
guardrails/resources/chat/chat.py
guardrails/resources/responses/__init__.py
guardrails/resources/responses/responses.py
guardrails/utils/__init__.py
guardrails/utils/anonymizer.py
guardrails/utils/context.py
guardrails/utils/conversation.py
guardrails/utils/create_vector_store.py
guardrails/utils/output.py
guardrails/utils/parsing.py
guardrails/utils/safety_identifier.py
guardrails/utils/schema.py
openai_guardrails-0.2.1.dist-info/METADATA
openai_guardrails-0.2.1.dist-info/WHEEL
openai_guardrails-0.2.1.dist-info/entry_points.txt
openai_guardrails-0.2.1.dist-info/licenses/LICENSE
openai_guardrails-0.2.1.dist-info/RECORD
