Metadata-Version: 2.4
Name: openai-guardrails
Version: 0.2.1
Summary: OpenAI Guardrails: A framework for building safe and reliable AI systems.
Project-URL: Homepage, https://openai.github.io/openai-guardrails-python/
Project-URL: Repository, https://github.com/openai/openai-guardrails-python
Author-email: OpenAI <support@openai.com>
License-Expression: MIT
License-File: LICENSE
Classifier: Intended Audience :: Developers
Classifier: License :: OSI Approved :: MIT License
Classifier: Operating System :: OS Independent
Classifier: Programming Language :: Python :: 3
Classifier: Programming Language :: Python :: 3.11
Classifier: Programming Language :: Python :: 3.12
Classifier: Programming Language :: Python :: 3.13
Classifier: Topic :: Software Development :: Libraries :: Python Modules
Classifier: Typing :: Typed
Requires-Python: >=3.11
Requires-Dist: openai-agents>=0.3.3
Requires-Dist: openai>=1.75.0
Requires-Dist: pip>=25.0.1
Requires-Dist: presidio-analyzer>=2.2.360
Requires-Dist: pydantic>=2.11.3
Requires-Dist: thinc>=8.3.6
Provides-Extra: benchmark
Requires-Dist: matplotlib>=3.7.0; extra == 'benchmark'
Requires-Dist: numpy>=1.24.0; extra == 'benchmark'
Requires-Dist: pandas>=2.0.0; extra == 'benchmark'
Requires-Dist: scikit-learn>=1.3.0; extra == 'benchmark'
Requires-Dist: seaborn>=0.12.0; extra == 'benchmark'
Provides-Extra: examples
Requires-Dist: pillow>=11.2.1; extra == 'examples'
Requires-Dist: rich>=14.0.0; extra == 'examples'
